CODE_OF_CONDUCT.md
LICENSE
MANIFEST.in
README.md
setup.cfg
setup.py
versioneer.py
rdkit_utilities/AllChem.py
rdkit_utilities/Chem.py
rdkit_utilities/__init__.py
rdkit_utilities/_version.py
rdkit_utilities/rdChemReactions.py
rdkit_utilities/rdDistGeom.py
rdkit_utilities/rdForceFieldHelpers.py
rdkit_utilities/rdMolAlign.py
rdkit_utilities/rdchem.py
rdkit_utilities/rdmolfiles.py
rdkit_utilities/rdmolops.py
rdkit_utilities/utilities.py
rdkit_utilities.egg-info/PKG-INFO
rdkit_utilities.egg-info/SOURCES.txt
rdkit_utilities.egg-info/dependency_links.txt
rdkit_utilities.egg-info/requires.txt
rdkit_utilities.egg-info/top_level.txt
rdkit_utilities/_io/__init__.py
rdkit_utilities/_io/_parser.py
rdkit_utilities/_io/_rdmolfiles.py
rdkit_utilities/tests/__init__.py
rdkit_utilities/tests/conftest.py
rdkit_utilities/tests/datafiles.py
rdkit_utilities/tests/test_chem.py
rdkit_utilities/tests/test_rdChemReactions.py
rdkit_utilities/tests/test_rdDistGeom.py
rdkit_utilities/tests/test_rdForceFieldHelpers.py
rdkit_utilities/tests/test_rdMolAlign.py
rdkit_utilities/tests/test_rdchem.py
rdkit_utilities/tests/test_rdmolops.py
rdkit_utilities/tests/test_utils.py
rdkit_utilities/tests/data/cch.pdb