Metadata-Version: 2.1
Name: rdkit-utilities
Version: 0.2.1
Author: Lily Wang
Author-email: lily.wang@anu.edu.au
License: MIT
Platform: Linux
Platform: Mac OS-X
Platform: Unix
Platform: Windows
Requires-Python: >=3.7
License-File: LICENSE
